pytol/__init__.py
pytol/classes/actions.py
pytol/classes/conditionals.py
pytol/classes/mission_objects.py
pytol/classes/objectives.py
pytol/classes/units.py
pytol/parsers/vtm_parser.py
pytol/parsers/vts_builder.py
pytol/resources/city_layouts_database.json
pytol/resources/equipment.py
pytol/resources/guid_to_name.json
pytol/resources/individual_prefabs_database.json
pytol/resources/noise.png
pytol/resources/resources.py
pytol/resources/vehicle_equip_database.json
pytol/terrain/mission_terrain_helper.py
pytol/terrain/terrain_calculator.py
pytol/visualization/README.md
pytol/visualization/__init__.py
pytol/visualization/visualizer.py
pytol-0.2.0.dist-info/METADATA
pytol-0.2.0.dist-info/WHEEL
pytol-0.2.0.dist-info/licenses/LICENSE
pytol-0.2.0.dist-info/RECORD
