Metadata-Version: 2.4
Name: pytol
Version: 0.2.0
Summary: Mission generation for VTOL VR with python.
Project-URL: Homepage, https://github.com/Fran-98/pytol
Project-URL: Issues, https://github.com/Fran-98/pytol/issues
Author-email: Fran-98 <franciscopvargas98@gmail.com>
License-Expression: GPL-3.0-only
License-File: LICENSE
Classifier: Operating System :: OS Independent
Classifier: Programming Language :: Python :: 3
Requires-Python: >=3.6
Requires-Dist: numpy
Requires-Dist: pillow
Requires-Dist: python-dotenv
Requires-Dist: scipy
Provides-Extra: all
Requires-Dist: pyvista; extra == 'all'
Provides-Extra: viz
Requires-Dist: pyvista; extra == 'viz'
